__init__.py
examples/blackpink_logo.py
examples/pornhub_logo.py
examples/thunder.py
source/textprome.py
textprome/__init__.py
textprome/textprome.py
textprome-1.0.dist-info/LICENSE
textprome-1.0.dist-info/METADATA
textprome-1.0.dist-info/WHEEL
textprome-1.0.dist-info/top_level.txt
textprome-1.0.dist-info/zip-safe
textprome-1.0.dist-info/RECORD
