Metadata-Version: 2.1
Name: textprome
Version: 1.0
Summary: Generate image from text with visual effects 
Home-page: https://github.com/jeremia49/TextPro.me
Author: jeremia49
Author-email: jeremia49@asia.com
License: MIT
Platform: UNKNOWN
Classifier: Programming Language :: Python :: 3
Classifier: License :: OSI Approved :: MIT License
Classifier: Operating System :: OS Independent
Requires-Python: >=3.5
Requires-Dist: bs4
Requires-Dist: requests
Requires-Dist: lxml
